oddoreven/__init__.py
oddoreven/cli.py
oddoreven/core.py
oddoreven_merlin-0.3.0.dist-info/licenses/LICENSE
oddoreven_merlin-0.3.0.dist-info/METADATA
oddoreven_merlin-0.3.0.dist-info/WHEEL
oddoreven_merlin-0.3.0.dist-info/entry_points.txt
oddoreven_merlin-0.3.0.dist-info/top_level.txt
oddoreven_merlin-0.3.0.dist-info/RECORD
