Metadata-Version: 2.4
Name: oddoreven-merlin
Version: 0.3.0
Summary: A simple Python library to check whether a number is odd or even
Home-page: 
Author: Merlin
Author-email: merlinfathima88@gmail.com
Requires-Python: >=3.7
License-File: LICENSE
Dynamic: author
Dynamic: author-email
Dynamic: description
Dynamic: description-content-type
Dynamic: license-file
Dynamic: requires-python
Dynamic: summary
